commandline_config/__init__.py
commandline_config/commandline_config.py
commandline_config-2.2.3.dist-info/LICENSE
commandline_config-2.2.3.dist-info/METADATA
commandline_config-2.2.3.dist-info/WHEEL
commandline_config-2.2.3.dist-info/top_level.txt
commandline_config-2.2.3.dist-info/RECORD
