Metadata-Version: 2.1
Name: commandline-config
Version: 2.2.3
Summary: A library for users to write (experiment in research) configurations in Python Dict or JSON format, while can read parameters from the command line
Home-page: https://github.com/NaiboWang/CommandlineConfig
Author: Naibo Wang
Author-email: naibowang@foxmail.com
Classifier: Programming Language :: Python :: 3
Classifier: License :: OSI Approved :: MIT License
Classifier: Operating System :: OS Independent
License-File: LICENSE
Requires-Dist: prettytable
